LICENSE
MANIFEST.in
README.rst
requirements.txt
setup.py
pie_time/__init__.py
pie_time/application.py
pie_time/card.py
pie_time.egg-info/PKG-INFO
pie_time.egg-info/SOURCES.txt
pie_time.egg-info/dependency_links.txt
pie_time.egg-info/entry_points.txt
pie_time.egg-info/not-zip-safe
pie_time.egg-info/requires.txt
pie_time.egg-info/top_level.txt
pie_time/cards/__init__.py
pie_time/cards/clock.py
pie_time/cards/picture.py
pie_time/cards/weather.py
pie_time/cards/resources/PTM55FT.ttf
pie_time/cards/resources/linea-weather-10.ttf
pie_time/cards/resources/opensans-light.ttf
pie_time/scripts/__init__.py
pie_time/scripts/pie_time.py