Metadata-Version: 1.1
Name: pie-time
Version: 1.0
Summary: Desk clock for your Raspberry Pi.
Home-page: https://pie-time.bthlabs.pl/
Author: Tomek Wójcik
Author-email: tomek@bthlabs.pl
License: https://git.bthlabs.pl/tomekwojcik/pie-time/src/master/LICENSE
Download-URL: https://git.bthlabs.pl/tomekwojcik/pie-time/archive/v1.0.tar.gz
Platform: any
